AUTHORS.rst
CONTRIBUTING.rst
HISTORY.rst
LICENSE
MANIFEST.in
README.rst
setup.cfg
setup.py
dbaas_dbmonitor/__init__.py
dbaas_dbmonitor/models.py
dbaas_dbmonitor/provider.py
dbaas_dbmonitor.egg-info/PKG-INFO
dbaas_dbmonitor.egg-info/SOURCES.txt
dbaas_dbmonitor.egg-info/dependency_links.txt
dbaas_dbmonitor.egg-info/not-zip-safe
dbaas_dbmonitor.egg-info/top_level.txt
dbaas_dbmonitor/migrations/0001_initial.py
dbaas_dbmonitor/migrations/__init__.py