Metadata-Version: 1.1
Name: dbaas-dbmonitor
Version: 0.2.2
Summary: Integration between dbaas and dbmonitor
Home-page: https://github.com/ricardosdias/dbaas_dbmonitor
Author: Ricardo Dias
Author-email: ricardo@ricardodias.org
License: BSD
Keywords: dbaas_dbmonitor
Platform: UNKNOWN
Classifier: Development Status :: 2 - Pre-Alpha
Classifier: Intended Audience :: Developers
Classifier: License :: OSI Approved :: BSD License
Classifier: Natural Language :: English
Classifier: Programming Language :: Python :: 2
Classifier: Programming Language :: Python :: 2.6
Classifier: Programming Language :: Python :: 2.7
Classifier: Programming Language :: Python :: 3
Classifier: Programming Language :: Python :: 3.3
